Metadata-Version: 2.1
Name: dice-prob-distribution
Version: 1.2
Summary: Gaussian and Binomial distributions calculations
Author: Desmond Odera
